ocacaptcha/__init__.py
ocacaptcha/captcha_nodriver.py
ocacaptcha/captcha_playwright.py
ocacaptcha/captcha_selenium.py
ocacaptcha/captcha_solver.py
ocacaptcha-0.2.54.dist-info/METADATA
ocacaptcha-0.2.54.dist-info/WHEEL
ocacaptcha-0.2.54.dist-info/top_level.txt
ocacaptcha-0.2.54.dist-info/RECORD
