Metadata-Version: 2.4
Name: ocacaptcha
Version: 0.2.54
Summary: This library for solving TikTok captcha via OCA captcha service
Home-page: https://github.com/OneClickAction/TikTok-Captcha-Solver
Author: OCA admin
Author-email: oneclickactionsoft@gmail.com
Keywords: tiktok,captcha,puzzle,slide,3d,two the same shapes,2 objects,rotate,whirl,circle,automation,python,selenium,playwright,nodriver,tiktok captcha,icon,tiktok slide,tiktok whirl,tiktok 3d,tiktok icon,geetest,geetest icon,datadome,slider,audio
Classifier: Programming Language :: Python :: 3
Classifier: License :: OSI Approved :: MIT License
Classifier: Operating System :: OS Independent
Requires-Python: >=3.13.1
Requires-Dist: requests
Requires-Dist: selenium
Requires-Dist: playwright
Requires-Dist: nodriver
Dynamic: author
Dynamic: author-email
Dynamic: classifier
Dynamic: description
Dynamic: description-content-type
Dynamic: home-page
Dynamic: keywords
Dynamic: requires-dist
Dynamic: requires-python
Dynamic: summary
